ahuri/__init__.py
ahuri/__main__.py
ahuri/config.py
ahuri/start.py
ahuri/utils.py
ahuri_cli-1.1.2.dist-info/LICENSE
ahuri_cli-1.1.2.dist-info/METADATA
ahuri_cli-1.1.2.dist-info/WHEEL
ahuri_cli-1.1.2.dist-info/entry_points.txt
ahuri_cli-1.1.2.dist-info/top_level.txt
ahuri_cli-1.1.2.dist-info/RECORD
