Metadata-Version: 2.1
Name: ahuri-cli
Version: 1.1.2
Summary: Use Ahuri from the command line!
Author: sqdnoises
License: The MIT License (MIT)
Project-URL: Homepage, https://github.com/ahuri-app/ahuri-cli
Classifier: Programming Language :: Python :: 3
Classifier: License :: OSI Approved :: MIT License
Classifier: Operating System :: OS Independent
Requires-Python: >=3.8
License-File: LICENSE
Requires-Dist: maskpass
Requires-Dist: requests
Requires-Dist: websockets
Requires-Dist: yarl
Provides-Extra: windows
Requires-Dist: pyreadline3 ; extra == 'windows'
